{
  "headline": "Thoughtful ideas, projects, and tools shaped through curiosity and research.",
  "identityLine": "Thinker. Learner. Problem Solver.",
  "subheadline": "Exploring automation, finance, science, technology, health, and systems thinking — one thoughtful project at a time.",
  "primaryCta": {
    "label": "View What I’m Building",
    "href": "/currently-building"
  },
  "secondaryCta": {
    "label": "Explore Research Notes",
    "href": "/articles"
  },
  "statusLine": "Currently researching caffeine performance systems",
  "tagline": "Automation · Finance · Science · Health",
  "visualImage": "/images/home/hero-visual.svg",
  "visualAlt": "Hero visual showing current focus and featured preview cards",
  "whatIDo": [
    { "icon": "🔬", "label": "Research notes with practical depth" },
    { "icon": "🛠", "label": "Projects and tools built in public" },
    { "icon": "📈", "label": "Frameworks for thinking and execution" },
    { "icon": "🧭", "label": "Curiosity-led exploration across disciplines" }
  ],
  "credentialFootnote": "Premium · Editorial · Trustworthy"
}
